sense_energy/__init__.py
sense_energy/asyncsenseable.py
sense_energy/plug_instance.py
sense_energy/py.typed
sense_energy/sense_api.py
sense_energy/sense_exceptions.py
sense_energy/sense_link.py
sense_energy/senseable.py
sense_energy-0.13.8.dist-info/licenses/LICENSE.txt
sense_energy-0.13.8.dist-info/METADATA
sense_energy-0.13.8.dist-info/WHEEL
sense_energy-0.13.8.dist-info/top_level.txt
sense_energy-0.13.8.dist-info/RECORD
