Metadata-Version: 2.4
Name: sense_energy
Version: 0.13.8
Summary: API for the Sense Energy Monitor
Home-page: https://github.com/scottbonline/sense
Download-URL: https://github.com/scottbonline/sense/archive/0.13.8.tar.gz
Author: scottbonline
Author-email: scottbonline@gmail.com
Keywords: sense,energy,api
Classifier: Programming Language :: Python :: 3
Classifier: Programming Language :: Python :: 3.9
Classifier: Programming Language :: Python :: 3.10
Classifier: Programming Language :: Python :: 3.11
Classifier: License :: OSI Approved :: MIT License
License-File: LICENSE.txt
Requires-Dist: async_timeout>=3.0.1
Requires-Dist: ciso8601
Requires-Dist: orjson
Requires-Dist: requests
Requires-Dist: websocket-client
Requires-Dist: websockets
Requires-Dist: aiohttp
Requires-Dist: kasa-crypt>=0.2.0
Dynamic: author
Dynamic: author-email
Dynamic: classifier
Dynamic: description
Dynamic: description-content-type
Dynamic: download-url
Dynamic: home-page
Dynamic: keywords
Dynamic: license-file
Dynamic: requires-dist
Dynamic: summary
